{
	"name": "PL_copydata",
	"properties": {
		"activities": [
			{
				"name": "Copy_0wu",
				"type": "Copy",
				"dependsOn": [
					{
						"activity": "Execute Pipeline1",
						"dependencyConditions": [
							"Succeeded"
						]
					}
				],
				"policy": {
					"timeout": "0.12:00:00",
					"retry": 0,
					"retryIntervalInSeconds": 30,
					"secureOutput": false,
					"secureInput": false
				},
				"userProperties": [
					{
						"name": "Source",
						"value": "consolidated-container/Customers/customer.csv"
					},
					{
						"name": "Destination",
						"value": "dbo.customer"
					}
				],
				"typeProperties": {
					"source": {
						"type": "DelimitedTextSource",
						"storeSettings": {
							"type": "AzureBlobStorageReadSettings",
							"recursive": true,
							"enablePartitionDiscovery": false
						},
						"formatSettings": {
							"type": "DelimitedTextReadSettings",
							"skipLineCount": 0
						}
					},
					"sink": {
						"type": "AzureSqlSink",
						"tableOption": "autoCreate"
					},
					"enableStaging": false,
					"validateDataConsistency": false,
					"translator": {
						"type": "TabularTranslator",
						"mappings": [
							{
								"source": {
									"name": "CustomerID",
									"type": "String",
									"physicalType": "String"
								},
								"sink": {
									"name": "CustomerID",
									"type": "String",
									"physicalType": "nvarchar"
								}
							},
							{
								"source": {
									"name": "FirstName",
									"type": "String",
									"physicalType": "String"
								},
								"sink": {
									"name": "FirstName",
									"type": "String",
									"physicalType": "nvarchar"
								}
							},
							{
								"source": {
									"name": "LastName",
									"type": "String",
									"physicalType": "String"
								},
								"sink": {
									"name": "LastName",
									"type": "String",
									"physicalType": "nvarchar"
								}
							},
							{
								"source": {
									"name": "Email",
									"type": "String",
									"physicalType": "String"
								},
								"sink": {
									"name": "Email",
									"type": "String",
									"physicalType": "nvarchar"
								}
							},
							{
								"source": {
									"name": "PhoneNumber",
									"type": "String",
									"physicalType": "String"
								},
								"sink": {
									"name": "PhoneNumber",
									"type": "String",
									"physicalType": "nvarchar"
								}
							},
							{
								"source": {
									"name": "Address",
									"type": "String",
									"physicalType": "String"
								},
								"sink": {
									"name": "Address",
									"type": "String",
									"physicalType": "nvarchar"
								}
							},
							{
								"source": {
									"name": "City",
									"type": "String",
									"physicalType": "String"
								},
								"sink": {
									"name": "City",
									"type": "String",
									"physicalType": "nvarchar"
								}
							},
							{
								"source": {
									"name": "State",
									"type": "String",
									"physicalType": "String"
								},
								"sink": {
									"name": "State",
									"type": "String",
									"physicalType": "nvarchar"
								}
							},
							{
								"source": {
									"name": "ZipCode",
									"type": "String",
									"physicalType": "String"
								},
								"sink": {
									"name": "ZipCode",
									"type": "String",
									"physicalType": "nvarchar"
								}
							},
							{
								"source": {
									"name": "Country",
									"type": "String",
									"physicalType": "String"
								},
								"sink": {
									"name": "Country",
									"type": "String",
									"physicalType": "nvarchar"
								}
							}
						],
						"typeConversion": true,
						"typeConversionSettings": {
							"allowDataTruncation": true,
							"treatBooleanAsNumber": false
						}
					}
				},
				"inputs": [
					{
						"referenceName": "SourceDataset_0wu",
						"type": "DatasetReference"
					}
				],
				"outputs": [
					{
						"referenceName": "DestinationDataset_0wu",
						"type": "DatasetReference"
					}
				]
			},
			{
				"name": "Execute Pipeline1",
				"type": "ExecutePipeline",
				"dependsOn": [],
				"policy": {
					"secureInput": false
				},
				"userProperties": [],
				"typeProperties": {
					"pipeline": {
						"referenceName": "PL_appending",
						"type": "PipelineReference"
					},
					"waitOnCompletion": true
				}
			}
		],
		"folder": {
			"name": "PL_copydata_practice"
		},
		"annotations": [],
		"lastPublishTime": "2024-08-27T06:55:25Z"
	},
	"type": "Microsoft.DataFactory/factories/pipelines"
}